[
        {
            "name": "Boruto Episode 143",
            "description": "Shintenshin no Jutsu yang Kalah dari Keripik Kentang.",
            "Rating": "8.72",
            "episode": 1,
            "categorie":"Action, Adventure, Martial Arts, Shounen, Super Power",
            "studio":"https://r2---sn-3jpm-hjpe.googlevideo.com/videoplayback?expire=1581559998&ei=PkBEXpfGB4_8uQWE6qfIAw&ip=192.187.124.122&id=99e2c23c5597d24b&itag=18&source=blogger&mm=31&mn=sn-3jpm-hjpe&ms=au&mv=m&mvi=1&pl=22&susc=bl&mime=video/mp4&dur=1434.296&lmt=1581249420124390&mt=1581531102&sparams=expire,ei,ip,id,itag,source,susc,mime,dur,lmt&sig=ALgxI2wwRgIhAMX9rl2_apAlTkU_6Qr4Cy2SLFvmALNWahx1_YQy9PChAiEAkvf5iPS3I3o4Svx4FHjvuHNAjidFM06kAL3_kGWpKA8%3D&lsparams=mm,mn,ms,mv,mvi,pl&lsig=AHylml4wRQIhAOLZckNxbS6VrU0TI0Vz7CnIXVkPmp_MZtk61bqw8wwEAiAldRqvqV9isdlPRLBGQ_FcUKg2Lpj9AQvWadsGRrZEeA%3D%3D",
            "img": "https://www.oploverz.in/wp-content/uploads/2017/04/6.jpg"
        },
        {
            "name": "One Piece Episode 921 ",
            "description": "Sudah Dimulai! Operasi Khusus untuk Menggulingkan Kaido!",
            "Rating": "8.72",
            "episode": 3,
            "categorie":"Action, Adventure, Comedy, Drama, Fantasy, Shounen, Super Power",
            "studio":"https://r1---sn-3jpm-hjpe.googlevideo.com/videoplayback?expire=1581559047&ei=hzxEXofnK4W4uQXi5YDgCw&ip=192.187.124.122&id=9afe7192b816cf53&itag=18&source=blogger&mm=31&mn=sn-3jpm-hjpe&ms=au&mv=m&mvi=0&pl=22&susc=bl&mime=video/mp4&dur=1430.906&lmt=1581218685295772&mt=1581530062&sparams=expire,ei,ip,id,itag,source,susc,mime,dur,lmt&sig=ALgxI2wwRQIgdOXfnhvhB1gfxAkhl58Zse8d4BT7Fs6bgskM6w9zrcYCIQDHgXe0GhUoorzPP7CQ6b5BWXUAUmsbJwS4pLtVQlc_NQ%3D%3D&lsparams=mm,mn,ms,mv,mvi,pl&lsig=AHylml4wRgIhANJ5evM3JFkesVDM_Lth04fzmUVua27nxHsbyPZHy6pCAiEAgCqRBbf-qz5GyV7wpD-HS9J7_DqqqguLCfxLIPq4P_Y%3D",
            "img": "https://www.oploverz.in/wp-content/uploads/2015/09/Screenshot_1.jpg"
        },
        {
            "name": "Naruto Shippuuden 500",
            "description": "Sebuah Pesan!",
            "Rating": "Rating Anime",
            "episode": 1,
            "categorie":"Action, Comedy, Martial Arts, Shounen, Super Power",
            "studio":"",
            "img": "https://www.oploverz.in/wp-content/uploads/2015/10/615.jpg"
        },
        {
            "name": "Boku no Hero Academia S3 Episode 25 ",
            "description": "Tak Tertandingi!",
            "Rating": "8.72",
            "episode": 4,
            "categorie":"Action, Adventure, Martial Arts, Shounen, Super Power",
            "studio":"",
            "img": "https://www.oploverz.in/wp-content/uploads/2018/04/1-11.jpg"
        },
        {
            "name": "Fairy Tail Episode 328",
            "description": "Teman-teman yang Tak Tergantikan!",
            "Rating": "8.72",
            "episode": 5,
            "categorie":"Action, Adventure, Martial Arts, Shounen, Super Power",
            "studio":"",
            "img": "https://www.oploverz.in/wp-content/uploads/2018/10/1-7.jpg"
        },
        {
            "name": "Sword Art Online Episode 25",
            "description": "Benih Dunia!",
            "Rating": "8.72",
            "episode": 1,
            "categorie":"Action, Adventure, Martial Arts, Shounen, Super Power",
            "studio":"",
            "img": "https://www.oploverz.in/wp-content/uploads/2015/11/2437.jpg"
        },
        {
            "name": "One Piece Movie 14 - Stampede!",
            "description": "One Piece Movie",
            "Rating": "8.72",
            "episode": 2,
            "categorie":"Action, Adventure, Martial Arts, Shounen, Super Power",
            "studio":"",
            "img": "https://www.oploverz.in/wp-content/uploads/2015/11/Stampede-Sub-Indo.jpg"
        },
        {
            "name": "One Punch Man S2 Episode 12",
            "description": "Pukulan Aliran Air Pemecah Batu!",
            "Rating": "8.72",
            "episode": 3,
            "categorie":"Action, Adventure, Martial Arts, Shounen, Super Power",
            "studio":"",
            "img": "https://www.oploverz.in/wp-content/uploads/2019/04/Screenshot_1.jpg"
        },
        {
            "name": "Infinite Dendrogram Episode 03",
            "description": "Superior!",
            "Rating": "8.72",
            "episode": 4,
            "categorie":"Action, Adventure, Martial Arts, Shounen, Super Power",
            "studio":"",
            "img": "https://www.oploverz.in/wp-content/uploads/2020/01/Screenshot_2.jpg"
        },
        {
            "name": "Black Clover Episode 118 Subtitle Indonesia",
            "description": "Reuni yang Melampaui Ruang dan Waktu!",
            "Rating": "Rating Anime",
            "episode": 10,
            "categorie":"Action, Adventure, Martial Arts, Shounen, Super Power",
            "studio":"Link Video",
            "img": "https://www.oploverz.in/wp-content/uploads/2017/10/Screenshot_1.jpg"
        }
        
        
]
