[
        {
            "path":"path",
            "name": "title",
            "description": "description",
            "Rating": "Rating",
            "episode": "episode",
            "categorie":"categorie",
            "studio":"urlstream",
            "img": "img"
        },
        {  
            "path":"path",
            "name": "title",
            "description": "description",
            "Rating": "Rating",
            "episode": "episode",
            "categorie":"categorie",
            "studio":"urlstream",
            "img": "img"
        },
        {
            "path":"path",
            "name": "title",
            "description": "description",
            "Rating": "Rating",
            "episode": "episode",
            "categorie":"categorie",
            "studio":"urlstream",
            "img": "img"
        },
        {
            "path":"path",
            "name": "title",
            "description": "description",
            "Rating": "Rating",
            "episode": "episode",
            "categorie":"categorie",
            "studio":"urlstream",
            "img": "img""
        },
        {
            "path":"path",
            "name": "title",
            "description": "description",
            "Rating": "Rating",
            "episode": "episode",
            "categorie":"categorie",
            "studio":"urlstream",
            "img": "img"
        },
        {
            "path":"path",
            "name": "title",
            "description": "description",
            "Rating": "Rating",
            "episode": "episode",
            "categorie":"categorie",
            "studio":"urlstream",
            "img": "img"
        },
        {
            "path":"path",
            "name": "title",
            "description": "description",
            "Rating": "Rating",
            "episode": "episode",
            "categorie":"categorie",
            "studio":"urlstream",
            "img": "img"
        },
        {
            "path":"path",
            "name": "title",
            "description": "description",
            "Rating": "Rating",
            "episode": "episode",
            "categorie":"categorie",
            "studio":"urlstream",
            "img": "img"
        },
        {
            "path":"path",
            "name": "title",
            "description": "description",
            "Rating": "Rating",
            "episode": "episode",
            "categorie":"categorie",
            "studio":"urlstream",
            "img": "img"
        },
        {
            "path":"path",
            "name": "title",
            "description": "description",
            "Rating": "Rating",
            "episode": "episode",
            "categorie":"categorie",
            "studio":"urlstream",
            "img": "img"
        }
       
       
]
